ifc5d/IFC4QtoBaseQuantities.json
ifc5d/IFC4QtoBaseQuantitiesBlender.json
ifc5d/IFC4X3QtoBaseQuantities.json
ifc5d/IFC4X3QtoBaseQuantitiesBlender.json
ifc5d/__init__.py
ifc5d/csv2ifc.py
ifc5d/ifc2json.py
ifc5d/ifc5Dspreadsheet.py
ifc5d/qto.py
ifc5d/typst_template_ifc_cost_schedule.typ
ifc5d-0.8.3.dist-info/METADATA
ifc5d-0.8.3.dist-info/WHEEL
ifc5d-0.8.3.dist-info/top_level.txt
ifc5d-0.8.3.dist-info/RECORD
