Metadata-Version: 2.4
Name: ifc5d
Version: 0.8.3
Summary: IFC 5D costing library for quantity take-off and schedule production
Author-email: Dion Moult <dion@thinkmoult.com>
Project-URL: Homepage, http://ifcopenshell.org
Project-URL: Documentation, https://docs.ifcopenshell.org
Project-URL: Issues, https://github.com/IfcOpenShell/IfcOpenShell/issues
Keywords: IFC,5D,BIM
Classifier: Programming Language :: Python :: 3
Classifier: License :: OSI Approved :: GNU Lesser General Public License v3 or later (LGPLv3+)
Requires-Dist: ifcopenshell
Provides-Extra: advanced
Requires-Dist: typst; extra == "advanced"
